pyTexecom/__init__.py
pyTexecom/texecom.py
pyTexecom-0.2.1.dist-info/METADATA
pyTexecom-0.2.1.dist-info/RECORD
pyTexecom-0.2.1.dist-info/WHEEL
pyTexecom-0.2.1.dist-info/top_level.txt
