Metadata-Version: 2.1
Name: pyTexecom
Version: 0.2.1
Summary: Texecom Interface Libary
Home-page: https://github.com/JDW2018/pyTexecom
Author: James Drew Williams
Author-email: james@jmtechnical.co.uk
License: UNKNOWN
Platform: UNKNOWN
Classifier: Programming Language :: Python :: 3
Classifier: License :: OSI Approved :: MIT License
Classifier: Operating System :: OS Independent
